xaudio/__init__.py
xaudio/_version.py
xaudio/api.py
xaudio/clients.py
xaudio/communication_handlers.py
xaudio/exceptions.py
xaudio/packetizer.py
xaudio/protocol/__init__.py
xaudio/protocol/interface.proto
xaudio/protocol/interface_pb2.py
xaudio/protocol/interface_pb2.pyi
xaudio/protocol/nanopb_pb2.py
xaudio-0.3.0.dist-info/licenses/LICENSE
xaudio-0.3.0.dist-info/METADATA
xaudio-0.3.0.dist-info/WHEEL
xaudio-0.3.0.dist-info/top_level.txt
xaudio-0.3.0.dist-info/RECORD
